datasans_pandamatic/__init__.py
datasans_pandamatic-0.2.4.dist-info/LICENSE
datasans_pandamatic-0.2.4.dist-info/METADATA
datasans_pandamatic-0.2.4.dist-info/WHEEL
datasans_pandamatic-0.2.4.dist-info/top_level.txt
datasans_pandamatic-0.2.4.dist-info/RECORD
