Metadata-Version: 2.2
Name: datasans-pandamatic
Version: 0.2.4
Summary: Llama-powered code generator for pandas dataframe processing
Author: Datasans
Author-email: datasans.id@gmail.com
Classifier: Programming Language :: Python :: 3
Classifier: License :: OSI Approved :: MIT License
Classifier: Operating System :: OS Independent
Requires-Python: >=3.7
License-File: LICENSE
Requires-Dist: pandas>=1.0.0
Requires-Dist: together>=0.2.0
Requires-Dist: ipython>=7.0.0
